gcp_logger/__init__.py
gcp_logger/custom_logger.py
gcp_logger/formatters.py
gcp_logger/handlers.py
gcp_logger/logger.py
gcp_logger-1.0.0.dist-info/METADATA
gcp_logger-1.0.0.dist-info/WHEEL
gcp_logger-1.0.0.dist-info/top_level.txt
gcp_logger-1.0.0.dist-info/RECORD
